examples/__init__.py
examples/compress_music.py
folder_compiler/__init__.py
folder_compiler/compiler.py
folder_compiler/context.py
folder_compiler/file_ownership_manager.py
folder_compiler/processors/__init__.py
folder_compiler/processors/base_processors.py
folder_compiler/processors/devnull_processor.py
folder_compiler/processors/file_copy_processor.py
folder_compiler/processors/utils/__init__.py
folder_compiler/processors/utils/pattern_filter.py
folder_compiler/processors/utils/processor_utils.py
folder_compiler-0.1.3.dist-info/LICENSE
folder_compiler-0.1.3.dist-info/METADATA
folder_compiler-0.1.3.dist-info/WHEEL
folder_compiler-0.1.3.dist-info/top_level.txt
folder_compiler-0.1.3.dist-info/RECORD
