Metadata-Version: 2.1
Name: folder-compiler
Version: 0.1.3
Summary: A simple util for 'compiling' a folder, e.g. to a static website.
Home-page: https://github.com/d-krupke/folder_compiler
Author: Dominik Krupke
Author-email: krupked@gmail.com
License: UNKNOWN
Platform: UNKNOWN
Classifier: Programming Language :: Python :: 3
Classifier: License :: OSI Approved :: MIT License
Classifier: Operating System :: OS Independent
Requires-Python: >=3.6
